lightautoml/__init__.py
lightautoml/addons/__init__.py
lightautoml/addons/autots/base.py
lightautoml/addons/hypex/__init__.py
lightautoml/addons/interpretation/__init__.py
lightautoml/addons/interpretation/data_process.py
lightautoml/addons/interpretation/l2x.py
lightautoml/addons/interpretation/l2x_model.py
lightautoml/addons/interpretation/lime.py
lightautoml/addons/interpretation/utils.py
lightautoml/addons/tabular_interpretation/__init__.py
lightautoml/addons/tabular_interpretation/sswarm.py
lightautoml/addons/uplift/__init__.py
lightautoml/addons/uplift/base.py
lightautoml/addons/uplift/metalearners.py
lightautoml/addons/uplift/metrics.py
lightautoml/addons/uplift/utils.py
lightautoml/addons/utilization/__init__.py
lightautoml/addons/utilization/utilization.py
lightautoml/automl/__init__.py
lightautoml/automl/base.py
lightautoml/automl/blend.py
lightautoml/automl/presets/__init__.py
lightautoml/automl/presets/base.py
lightautoml/automl/presets/image_config.yml
lightautoml/automl/presets/image_presets.py
lightautoml/automl/presets/tabular_config.yml
lightautoml/automl/presets/tabular_configs/conf_0_sel_type_0.yml
lightautoml/automl/presets/tabular_configs/conf_1_sel_type_1.yml
lightautoml/automl/presets/tabular_configs/conf_2_select_mode_1_no_typ.yml
lightautoml/automl/presets/tabular_configs/conf_3_sel_type_1_no_inter_lgbm.yml
lightautoml/automl/presets/tabular_configs/conf_4_sel_type_0_no_int.yml
lightautoml/automl/presets/tabular_configs/conf_5_sel_type_1_tuning_full.yml
lightautoml/automl/presets/tabular_configs/conf_6_sel_type_1_tuning_full_no_int_lgbm.yml
lightautoml/automl/presets/tabular_presets.py
lightautoml/automl/presets/text_config.yml
lightautoml/automl/presets/text_presets.py
lightautoml/automl/presets/time_series_config.yml
lightautoml/automl/presets/utils.py
lightautoml/automl/presets/whitebox_config.yml
lightautoml/automl/presets/whitebox_presets.py
lightautoml/dataset/__init__.py
lightautoml/dataset/base.py
lightautoml-0.4.2.dist-info/LICENSE
lightautoml-0.4.2.dist-info/METADATA
lightautoml-0.4.2.dist-info/WHEEL
lightautoml-0.4.2.dist-info/RECORD
