Metadata-Version: 2.3
Name: LightAutoML
Version: 0.4.2
Summary: Fast and customizable framework for automatic ML model creation (AutoML)
License: Apache-2.0
Author: Alexander Ryzhkov
Author-email: alexmryzhkov@gmail.com
Requires-Python: >=3.8
Classifier: Development Status :: 5 - Production/Stable
Classifier: Environment :: Console
Classifier: Intended Audience :: Science/Research
Classifier: License :: OSI Approved :: Apache Software License
Classifier: Natural Language :: English
Classifier: Operating System :: OS Independent
Classifier: Programming Language :: Python :: 3
Classifier: Programming Language :: Python :: 3.8
Classifier: Programming Language :: Python :: 3.9
Classifier: Programming Language :: Python :: 3.10
Classifier: Programming Language :: Python :: 3.11
Classifier: Programming Language :: Python :: 3.12
Classifier: Programming Language :: Python :: 3.13
Classifier: Topic :: Scientific/Engineering :: Artificial Intelligence
Classifier: Typing :: Typed
Provides-Extra: afg
Provides-Extra: all
Provides-Extra: cv
Provides-Extra: hypex
Provides-Extra: nlp
Provides-Extra: report
Requires-Dist: PyWavelets ; extra == "cv" or extra == "all"
Requires-Dist: SQLAlchemy (>=2.0)
Requires-Dist: albumentations (<=1.0.3) ; extra == "cv" or extra == "all"
Requires-Dist: autowoe (>=1.3.3)
Requires-Dist: catboost (>=0.26.1)
Requires-Dist: cffi (==1.14.5) ; extra == "report" or extra == "all"
Requires-Dist: cmaes
Requires-Dist: fasttext-numpy2 ; extra == "nlp" or extra == "all"
Requires-Dist: featuretools (>=1.11.1) ; extra == "afg" or extra == "all"
Requires-Dist: holidays
Requires-Dist: hypex ; extra == "hypex"
Requires-Dist: jinja2
Requires-Dist: joblib
Requires-Dist: json2html
Requires-Dist: lightgbm (>=2.3)
Requires-Dist: lightgbm (>=4.4.0,<5.0.0) ; sys_platform == "darwin"
Requires-Dist: networkx
Requires-Dist: nltk ; extra == "nlp" or extra == "all"
Requires-Dist: numpy
Requires-Dist: numpy (>=1.22) ; python_version >= "3.10"
Requires-Dist: opencv-python (<=4.8.0.74) ; extra == "cv" or extra == "all"
Requires-Dist: optuna
Requires-Dist: pandas
Requires-Dist: poetry-core (>=1.0.0,<2.0.0)
Requires-Dist: pyyaml
Requires-Dist: scikit-learn (>=0.22)
Requires-Dist: scipy (<=1.11) ; python_version < "3.9"
Requires-Dist: scipy ; python_version >= "3.9"
Requires-Dist: seaborn
Requires-Dist: statsmodels (<=0.14.0)
Requires-Dist: tabicl ; python_version >= "3.9" and python_version < "4.0"
Requires-Dist: tabm ; python_version >= "3.9"
Requires-Dist: timm (>=0.9.0) ; extra == "cv"
Requires-Dist: torch (>=1.9.0)
Requires-Dist: torchvision ; extra == "cv" or extra == "all"
Requires-Dist: tqdm
Requires-Dist: transformers (>=4) ; extra == "nlp" or extra == "all"
Requires-Dist: weasyprint (==52.5) ; extra == "report" or extra == "all"
Requires-Dist: xgboost (>=2.0.0,<3.0.0)
Project-URL: Homepage, https://lightautoml.readthedocs.io/en/latest/
Project-URL: Repository, https://github.com/sb-ai-lab/LightAutoML
